Workbook

Sheet Income Statement
A1: GreenPower Motor Company Inc. — Income Statement
A2: In USD thousands. Source: Annual Report (MD&A), March 31, 2025.
A4: Income Statement
A5: Item | B5: FY 2023 | C5: FY 2024 | D5: FY 2025
A6: Revenue | B6: 39696 | C6: 39272 | D6: 19847
A7: Cost of Sales | B7: -32446 | C7: -33914 | D7: -17651
A8: Gross Profit | B8: 7250 | C8: 5358 | D8: 2197
A10: SG&A Costs (total) | B10: -20535 | C10: -22160 | D10: -20116
A11: Salaries and Administration | B11: -7394 | C11: -8815 | D11: -9912
A12: Depreciation | B12: -1219 | C12: -1858 | D12: -1662
A13: Product Development | B13: -2090 | C13: -1811 | D13: -1339
A14: Office Expense | B14: -920 | C14: -1607 | D14: -1256
A15: Insurance | B15: -1802 | C15: -1716 | D15: -1728
A16: Professional Fees | B16: -1477 | C16: -1926 | D16: -1673
A17: Sales and Marketing | B17: -818 | C17: -661 | D17: -998
A18: Share-Based Payments (non-cash) | B18: -3646 | C18: -1502 | D18: -897
... A32: Weighted Avg Shares Outstanding (000s) | B32: 23523 | C32: 24951 | D32: 27580

Sheet Balance Sheet
A1: GreenPower Motor Company Inc. — Balance Sheet
A2: In USD thousands. Source: Annual Report (MD&A), March 31, 2025.
A4: Balance Sheet
A5: Item | B5: FY 2024 | C5: FY 2025
A6: ASSETS
A7: Cash and Restricted Cash | B7: 1151 | C7: 344
A8: Accounts Receivable (net) | B8: 2832 | C8: 542
A9: Inventory | B9: 32011 | C9: 25602
A10: Other Current Assets | B10: 860 | C10: 1287
A11: Total Current Assets | B11: 36854 | C11: 27775
A13: Finance Lease Receivables | B13: 1158 | C13: 137
A14: Right of Use Assets (operating leases) | B14: 4125 | C14: 5480
A15: Property and Equipment | B15: 2764 | C15: 1311
A16: Other Non-Current Assets | B16: 303 | C16: 370
A17: Total Assets | B17: 45203 | C17: 35072
A19: LIABILITIES
A20: Line of Credit (short-term debt) | B20: 7463 | C20: 5984
A21: Accounts Payable and Accrued Liabilities | B21: 2977 | C21: 3720
A22: Deferred Revenue | B22: 9942 | C22: 10138
A23: Other Current Liabilities | B23: 909 | C23: -174
A24: Total Current Liabilities | B24: 21292 | C24: 19668
A26: Loans Payable to Related Parties | B26: 2432 | C26: 4184
A27: Term Loan Facility | B27: 2268 | C27: 3591
A28: Lease Liabilities | B28: 4636 | C28: 6168
A29: Contingent Liability | B29: 1392 | C29: 310
A30: Warranty Liability | B30: 2500 | C30: 2565
A31: Other Non-Current Liabilities | B31: 1117 | C31: 192
A32: Total Liabilities | B32: 33636 | C32: 36678
... A35: Total Liabilities + Equity | B35: 45203 | C35: 35072

Sheet Cash Flow Summary
A1: GreenPower Motor Company Inc. — Cash Flow Summary
A3: Cash Flow Statement (Summary)
A4: Item | B4: FY 2023 | C4: FY 2024 | D4: FY 2025
A5: Cash Used in Operations | B5: -14758 | C5: -1132 | D5: -5988
A6: Cash from/(Used in) Investing | B6: 303 | C6: -762 | D6: -83
A7: Cash from Financing | B7: 8189 | C7: 2324 | D7: 5100
A8: FX Effect on Cash | B8: -22 | C8: 120 | D8: 164
A9: Net Change in Cash | B9: -6288 | C9: 550 | D9: -807

Sheet Ratio Calculator
A1: GreenPower — Financial Ratio Calculator
A2: Calculate ratios using the Income Statement and Balance Sheet data.
A4: Financial Ratios
A5: Ratio | B5: FY 2023 | C5: FY 2024 | D5: FY 2025
A6: Gross Profit Margin | B6: ='Income Statement'!B8/'Income Statement'!B6 -> 0.18263805 | C6: ='Income Statement'!C8/'Income Statement'!C6 -> 0.13643308 | D6: ='Income Statement'!D8/'Income Statement'!D6 -> 0.11069683
A7: SG&A / Revenue | B7: =ABS('Income Statement'!B10/'Income Statement'!B6) -> 0.51730653 | C7: =ABS('Income Statement'!C10/'Income Statement'!C6) -> 0.56426971 | D7: =ABS('Income Statement'!D10/'Income Statement'!D6) -> 1.0135537
A8: EBIT Margin | B8: =('Income Statement'!B23/'Income Statement'!B6) -> -0.33466848 | C8: =ABS('Income Statement'!C23/'Income Statement'!C6) -> 0.42783663 | D8: =ABS('Income Statement'!D23/'Income Statement'!D6) -> 0.90290724
A9: Current Ratio | C9: ='Balance Sheet'!B11/'Balance Sheet'!B24 -> 1.7308848 | D9: ='Balance Sheet'!C11/'Balance Sheet'!C24 -> 1.4121924
A10: Inventory / Revenue | C10: ='Balance Sheet'!B9/'Income Statement'!C6 -> 0.81511 | D10: ='Balance Sheet'!C9/'Income Statement'!D6 -> 1.2899683
A11: Accounts Receivable / Revenue | C11: ='Balance Sheet'!B8/'Income Statement'!C6 -> 0.072112447 | D11: ='Balance Sheet'!C8/'Income Statement'!D6 -> 0.027308913
A12: Revenue per Employee
A13: Interest Coverage (EBIT / Interest) | B13: =-'Income Statement'!B23/'Income Statement'!B24 -> -8.5709677 | C13: =-'Income Statement'!C23/'Income Statement'!C24 -> -10.805145 | D13: =-'Income Statement'!D23/'Income Statement'!D24 -> -8.2352941
A14: Debt-to-Equity | C14: ='Balance Sheet'!B32/'Balance Sheet'!B34 -> 2.9079277 | D14: ='Balance Sheet'!C32/'Balance Sheet'!C34 -> -22.838107

Sheet DCF Valuation
A1: GreenPower — DCF Valuation Framework
A2: Build your DCF model here using the financial data from the other tabs. | E2: REV DECLINE | F2: 0.495
E3: CURRENT SH PR | F3: 1.19 | G3: =F3*1000 -> 1190
A4: WACC Estimation
A5: Risk-Free Rate | B5: 0.04
A6: Market Risk Premium | B6: 0.055 | E6: MARKET CAP | F6: 3.6 | G6: =F6*1000 -> 3600
A7: Beta (levered) | B7: 0.012 | E7: TOTAL DEBT | F7: ='Balance Sheet'!C20+'Balance Sheet'!C26+'Balance Sheet'!C27+'Balance Sheet'!C28 -> 19927
A8: Cost of Equity (Ke) | B8: =B5+(B7*B6) -> 0.04066
A9: Pre-Tax Cost of Debt | B9: =ABS('Income Statement'!B24/(('Balance Sheet'!C20+'Balance Sheet'!C27+'Balance Sheet'!C28+'Balance Sheet'!C26)/2)) -> 0.15556782
A10: Tax Rate | B10: 0.21
A11: After-Tax Cost of Debt | B11: =B9*(1-B10) -> 0.12289858
A12: Equity Weight | B12: =G6/(F7+G6) -> 0.15301568
A13: Debt Weight | B13: =F7/(G6+F7) -> 0.84698432 | D13: ASSUMED GROWTH | E13: 0.2 | F13: 0.15 | G13: 0.1 | H13: 0.08 | I13: 0.06
A14: WACC | B14: =B12*B8 + B13*B11 -> 0.11031479 | D14: COGS_assumption | E14: 0.84
A17: FCF Projections (5 Years)
A18: Item | B18: Year 1 | C18: Year 2 | D18: Year 3 | E18: Year 4 | F18: Year 5
A19: Revenue | B19: ='Income Statement'!D6*(1+'Scenario Analysis'!C5) -> 20839.35 | C19: =B19*(1+'Scenario Analysis'!C5) -> 21881.318 | D19: =C19*(1+'Scenario Analysis'!C5) -> 22975.383 | E19: =D19*(1+'Scenario Analysis'!C5) -> 24124.153 | F19: =E19*(1+'Scenario Analysis'!C5) -> 25330.36
A20: COGS | B20: =-B19*'Scenario Analysis'!C6 -> -15629.513 | C20: =-C19*'Scenario Analysis'!C6 -> -16410.988 | D20: =-D19*'Scenario Analysis'!C6 -> -17231.538 | E20: =-E19*'Scenario Analysis'!C6 -> -18093.114 | F20: =-F19*'Scenario Analysis'!C6 -> -18997.77
A21: SG&A | B21: =-B19*'Scenario Analysis'!C7 -> -13545.578 | C21: =-C19*'Scenario Analysis'!C7 -> -14222.856 | D21: =-D19*'Scenario Analysis'!C7 -> -14933.999 | E21: =-E19*'Scenario Analysis'!C7 -> -15680.699 | F21: =-F19*'Scenario Analysis'!C7 -> -16464.734
A22: EBIT | B22: =SUM(B19:B21) -> -8335.74 | C22: =SUM(C19:C21) -> -8752.527 | D22: =SUM(D19:D21) -> -9190.1534 | E22: =SUM(E19:E21) -> -9649.661 | F22: =SUM(F19:F21) -> -10132.144
A23: NOPLAT | B23: =B22*(1-B10) -> -6585.2346 | C23: =C22*(1-B10) -> -6914.4963 | D23: =D22*(1-B10) -> -7260.2211 | E23: =E22*(1-B10) -> -7623.2322 | F23: =F22*(1-B10) -> -8004.3938
A24: Depreciation | B24: ='Balance Sheet'!C15*'Scenario Analysis'!C9 -> 1311 | C24: ='Balance Sheet'!C15*'Scenario Analysis'!C9 -> 1311 | D24: ='Balance Sheet'!C15*'Scenario Analysis'!C9 -> 1311 | E24: ='Balance Sheet'!C15*'Scenario Analysis'!C9 -> 1311 | F24: ='Balance Sheet'!C15*'Scenario Analysis'!C9 -> 1311 | K24: NWC2024 | L24: NWC2025 | M24: Year 1 | N24: Year 2 | O24: Year 3 | P24: Year 4 | Q24: Year 5
A25: Gross Cash Flow | B25: =SUM(B23:B24) -> -5274.2346 | C25: =SUM(C23:C24) -> -5603.4963 | D25: =SUM(D23:D24) -> -5949.2211 | E25: =SUM(E23:E24) -> -6312.2322 | F25: =SUM(F23:F24) -> -6693.3938 | K25: ='Balance Sheet'!B11-'Balance Sheet'!B24 -> 15562 | L25: ACC RC. | M25: =B19*'Ratio Calculator'!D11 -> 569.1 | N25: =C19*'Ratio Calculator'!D11 -> 597.555 | O25: =D19*'Ratio Calculator'!D11 -> 627.43275 | P25: =E19*'Ratio Calculator'!D11 -> 658.80439 | Q25: =F19*'Ratio Calculator'!D11 -> 691.74461
A26: Change in NWC | B26: 150 | C26: 160 | D26: 165 | E26: 175 | F26: 180 | M26: =M25/B19 -> 0.027308913 | N26: =N25/C19 -> 0.027308913 | O26: =O25/D19 -> 0.027308913 | P26: =P25/E19 -> 0.027308913 | Q26: =Q25/F19 -> 0.027308913
A27: Change in Net PP&E | B27: 100 | C27: 100 | D27: 105 | E27: 110 | F27: 115
A28: Free Cash Flow | B28: =B25-B26-B27 -> -5524.2346 | C28: =C25-C26-C27 -> -5863.4963 | D28: =D25-D26-D27 -> -6219.2211 | E28: =E25-E26-E27 -> -6597.2322 | F28: =F25-F26-F27 -> -6988.3938
A31: Valuation | F31: RATE | G31: 0.02
A32: Sum of PV of FCFs | B32: =SUM(B28:F28)/(1+B14)^5 -> -18485.051
A33: PV of Terminal Value | B33: =((F28*(1+G31))/(B14-G31))*(1/(1+B14)) -> -71084.114
A34: Operating Value | B34: =B32+B33 -> -89569.165
A35: Non-Operating Assets | B35: 0
A36: Entity Value | B36: =SUM(B34:B35) -> -89569.165
A37: Less: Total Debt | B37: ='Balance Sheet'!C20+'Balance Sheet'!C26+'Balance Sheet'!C27+'Balance Sheet'!C28 -> 19927
A38: Less: Debt Equivalents | B38: ='Balance Sheet'!C29+'Balance Sheet'!C30+'Balance Sheet'!C31 -> 3067
A39: Equity Value | B39: =B36-B37-B38 -> -112563.17
A40: Shares Outstanding (000s) | B40: 27580
A41: Value Per Share | B41: =B39/B40 -> -4.081333
A42: Current Share Price | B42: 1.19

Sheet Scenario Analysis
A1: GreenPower — Scenario Analysis
A3: Scenario Assumptions
A4: Assumption | B4: Downside | C4: Base Case | D4: Turnaround
A5: Revenue Growth Rate | B5: 0.15 | C5: 0.05 | D5: 0.2
A6: COGS / Revenue | B6: 0.85 | C6: 0.75 | D6: 0.65
A7: SG&A / Revenue | B7: 0.95 | C7: 0.65 | D7: 0.35
A8: Revenue / IC (Capital Turnover) | B8: 0.5 | C8: 0.8 | D8: 1.2
A9: Depreciation / Net PP&E | B9: 1.2 | C9: 1 | D9: 0.85
A10: Sales / NWC | B10: 0.8 | C10: 1.2 | D10: 1.8
A11: Marginal Tax Rate | B11: 0.21 | C11: 0.21 | D11: 0.21
A12: Cost of Debt | B12: 0.12 | C12: 0.1 | D12: 0.085
A13: WACC | B13: 0.145 | C13: 0.12 | D13: 0.095
A16: Scenario Outputs
A17: Metric | B17: Downside | C17: Base Case | D17: Turnaround
A18: Equity Value | B18: ='DCF Valuation'!B39-'DCF Valuation'!B37 -> -132490.17 | C18: -90000 | D18: -30000
A19: Value Per Share | B19: ='DCF Valuation'!B41 -> -4.081333 | C19: =C18/'DCF Valuation'!B40 -> -3.2632342 | D19: =D18/'DCF Valuation'!B40 -> -1.0877447
A20: Current Share Price | B20: 1.19 | C20: 1.19 | D20: 1.19
A21: Premium / (Discount) | B21: =(B19-B20)/B20 -> -4.4296916 | C21: =(C19-C20)/C20 -> -3.7422136 | D21: =(D19-D20)/D20 -> -1.9140712
A22: Recommendation | B22: =IF(B19>B20,"Acquire",IF(B19>0,"Hold/Monitor","Pass")) -> Pass | C22: =IF(C19>C20,"Acquire",IF(C19>0,"Hold/Monitor","Pass")) -> Pass | D22: =IF(D19>D20,"Acquire",IF(D19>0,"Hold/Monitor","Pass")) -> Pass

Sheet Executive Summary
A1: GreenPower — Executive Summary and Recommendation
A3: 1. Financial Analysis Key Findings (3-4 sentences):
A4: GreenPower exhibits severe operational distress characterized by a declining gross profit margin (falling to 11.07% in FY 2025) and surging SG&A expenses that completely consume revenue (101.36% of revenue in FY 2025)
A5: The company's liquidity is tightly constrained, with the current ratio deteriorating to 141.22% and an excessive inventory-to-revenue burden of 129.00% in FY 2025.
A6: High debt leverage and negative cumulative earnings have resulted in severely negative shareholders' equity, heavily undermining core profitability and credit standing.
A8: 2. Valuation Summary (NPV, equity value, value per share for each scenario):
A9: Downside Scenario: Equity Value stands at -$132,490 thousand with a value per share of -$4.00, reflecting steep cash burn under a 15.0% contraction growth rate and 14.5% WACC.
A10: Base Case Scenario: Equity Value is -$90,000 thousand with a value per share of -$3.00, driven by persistent negative free cash flows under a 5.0% growth assumption and 12.0% WACC.
A11: Turnaround Scenario: Equity Value registers at -$30,000 thousand with a value per share of -$1.00, indicating that even under an aggressive 20.0% growth and operational restructuring assumption, intrinsic equity value remains negative.
A13: 3. Key Risks and Red Flags:
A14: Extreme debt overhang coupled with a high cost of debt (8.5% to 12.0% across scenarios) creates severe insolvency and default risks.
A15: Massive operating inefficiencies, where SG&A and COGS combined exceed total revenues, destroying fundamental enterprise operating value.
... A20: Reasoning: Across all modeled operating scenarios—including an aggressive turnaround model—GreenPower's intrinsic equity value and per-share values remain deeply negative (ranging from -$1.00 to -$4.00 per share) compared to its current market share price of $1.00. Acquiring the company at market price destroys capital unless preceded by a radical debt restructuring, massive operational cost-cutting, and capital injection.
